bosskit/__init__.py
bosskit/__main__.py
bosskit/_version.py
bosskit/main.py
bosskit-0.0.1.dist-info/licenses/LICENSE
bosskit-0.0.1.dist-info/METADATA
bosskit-0.0.1.dist-info/WHEEL
bosskit-0.0.1.dist-info/entry_points.txt
bosskit-0.0.1.dist-info/top_level.txt
bosskit-0.0.1.dist-info/RECORD
