Metadata-Version: 2.4
Name: bosskit
Version: 0.0.1
Summary: BossNet AI Agent Toolkit - Python library for building AI-powered agents
Author-email: BossNet <info@boss-net.com>
Project-URL: Homepage, https://github.com/boss-net/ai-masterclass
Project-URL: Documentation, https://bosskit.readthedocs.io/
Project-URL: Issues, https://github.com/boss-net/ai-masterclass/issues
Keywords: ai,machine learning,agents,python
Classifier: Development Status :: 4 - Beta
Classifier: Environment :: Console
Classifier: Intended Audience :: Developers
Classifier: License :: OSI Approved :: Apache Software License
Classifier: Programming Language :: Python :: 3
Classifier: Programming Language :: Python :: 3.11
Classifier: Programming Language :: Python :: 3.12
Classifier: Programming Language :: Python :: 3.13
Classifier: Programming Language :: Python :: 3 :: Only
Classifier: Topic :: Scientific/Engineering :: Artificial Intelligence
Classifier: Topic :: Software Development :: Libraries
Classifier: Operating System :: OS Independent
Requires-Python: <3.14,>=3.8
License-File: LICENSE
Dynamic: license-file
